guestbook/__init__.py
guestbook/static/main.css
guestbook/templates/index.html
Rambo_zhou_guestbook-1.0.1.dist-info/METADATA
Rambo_zhou_guestbook-1.0.1.dist-info/WHEEL
Rambo_zhou_guestbook-1.0.1.dist-info/entry_points.txt
Rambo_zhou_guestbook-1.0.1.dist-info/top_level.txt
Rambo_zhou_guestbook-1.0.1.dist-info/RECORD
