Metadata-Version: 2.1
Name: Rambo-zhou-guestbook
Version: 1.0.1
Summary: A guestbook web application.
Home-page: https://rambo_zhou@bitbucket.org/rambo_zhou/guestbook/
Author: rambo_zhou
Author-email: zjy13929412080139@126.com
License: BSD License
Keywords: web,guestbook
Platform: UNKNOWN
Classifier: Development Status :: 4 - Beta
Classifier: Framework :: Flask
Classifier: License :: OSI Approved :: BSD License
Classifier: Programming Language :: Python
Classifier: Programming Language :: Python :: 3.6
Requires-Dist: Flask
